crossentropy_triton/__init__.py
crossentropy_triton/causalLMloss.py
crossentropy_triton/crossentropy_tl.py
crossentropy_triton-0.1.2.dist-info/licenses/LICENSE
crossentropy_triton-0.1.2.dist-info/METADATA
crossentropy_triton-0.1.2.dist-info/WHEEL
crossentropy_triton-0.1.2.dist-info/top_level.txt
crossentropy_triton-0.1.2.dist-info/RECORD
