Metadata-Version: 2.4
Name: crossentropy-triton
Version: 0.1.2
Summary: A high-performance, memory-efficient cross-entropy loss implementation using Triton for CUDA GPUs
Home-page: https://github.com/Dcas89/crossentropy-triton
Author: Daniel Castillo
Author-email: d.castillocastagneto@gmail.com
Project-URL: Bug Reports, https://github.com/Dcas89/crossentropy-triton/issues
Project-URL: Source, https://github.com/Dcas89/crossentropy-triton
Keywords: triton,cuda,cross-entropy,machine-learning,deep-learning,pytorch
Classifier: Development Status :: 4 - Beta
Classifier: Intended Audience :: Developers
Classifier: Intended Audience :: Science/Research
Classifier: License :: OSI Approved :: MIT License
Classifier: Operating System :: OS Independent
Classifier: Programming Language :: Python :: 3.9
Classifier: Programming Language :: Python :: 3.10
Classifier: Programming Language :: Python :: 3.11
Classifier: Programming Language :: Python :: 3.12
Classifier: Topic :: Scientific/Engineering :: Artificial Intelligence
Classifier: Topic :: Software Development :: Libraries :: Python Modules
Requires-Python: >=3.9
License-File: LICENSE
Requires-Dist: torch>=2.6.0
Requires-Dist: triton>=3.3.0
Dynamic: author
Dynamic: author-email
Dynamic: classifier
Dynamic: description
Dynamic: description-content-type
Dynamic: home-page
Dynamic: keywords
Dynamic: license-file
Dynamic: project-url
Dynamic: requires-dist
Dynamic: requires-python
Dynamic: summary
